README.rst
setup.py
django_nginx_image.egg-info/PKG-INFO
django_nginx_image.egg-info/SOURCES.txt
django_nginx_image.egg-info/dependency_links.txt
django_nginx_image.egg-info/not-zip-safe
django_nginx_image.egg-info/requires.txt
django_nginx_image.egg-info/top_level.txt
nginx_image/__init__.py
nginx_image/management/__init__.py
nginx_image/management/commands/__init__.py
nginx_image/management/commands/nginx_image_converter.py
nginx_image/templatetags/__init__.py
nginx_image/templatetags/nginx_image.py