Metadata-Version: 1.1
Name: django-nginx-image
Version: 0.3.2
Summary: Resizing and cropping images via Nginx, and cache the result
Home-page: http://github.com/adw0rd/django-nginx-image
Author: Mikhail Andreev
Author-email: x11org@gmail.com
License: BSD
Keywords: django,nginx,image,resize,crop,cache
Platform: UNKNOWN
Classifier: Environment :: Web Environment
Classifier: Programming Language :: Python
Classifier: Framework :: Django
Classifier: License :: OSI Approved :: BSD License
Classifier: Topic :: Software Development :: Libraries :: Application Frameworks
Classifier: Topic :: Software Development :: Libraries :: Python Modules
